powerletrics/Makefile
powerletrics/__init__.py
powerletrics/config.conf
powerletrics/ebpf_python.c
powerletrics/powerletrics.py
powerletrics/__pycache__/powerletrics.cpython-312.pyc
powerletrics/http/index.html
powerletrics/http/logo.png
powerletrics/http/script.js
powerletrics/http/static/datatables.min.css
powerletrics/http/static/datatables.min.js
powerletrics/http/static/echarts.min.js
powerletrics/http/static/jquery-3.7.1.min.js
powerletrics/http/static/semantic.min.css
powerletrics/http/static/semantic.min.js
powerletrics/http/static/themes/basic/assets/fonts/icons.woff
powerletrics/http/static/themes/basic/assets/fonts/icons.woff2
powerletrics/http/static/themes/default/assets/fonts/Lato-Bold.woff
powerletrics/http/static/themes/default/assets/fonts/Lato-Bold.woff2
powerletrics/http/static/themes/default/assets/fonts/Lato-BoldItalic.woff
powerletrics/http/static/themes/default/assets/fonts/Lato-BoldItalic.woff2
powerletrics/http/static/themes/default/assets/fonts/Lato-Italic.woff
powerletrics/http/static/themes/default/assets/fonts/Lato-Italic.woff2
powerletrics/http/static/themes/default/assets/fonts/Lato-Regular.woff
powerletrics/http/static/themes/default/assets/fonts/Lato-Regular.woff2
powerletrics/http/static/themes/default/assets/fonts/LatoLatin-Bold.woff
powerletrics/http/static/themes/default/assets/fonts/LatoLatin-Bold.woff2
powerletrics/http/static/themes/default/assets/fonts/LatoLatin-BoldItalic.woff
powerletrics/http/static/themes/default/assets/fonts/LatoLatin-BoldItalic.woff2
powerletrics/http/static/themes/default/assets/fonts/LatoLatin-Italic.woff
powerletrics/http/static/themes/default/assets/fonts/LatoLatin-Italic.woff2
powerletrics/http/static/themes/default/assets/fonts/LatoLatin-Regular.woff
powerletrics/http/static/themes/default/assets/fonts/LatoLatin-Regular.woff2
powerletrics/http/static/themes/default/assets/fonts/brand-icons.woff
powerletrics/http/static/themes/default/assets/fonts/brand-icons.woff2
powerletrics-0.0.5.dist-info/LICENSE
powerletrics-0.0.5.dist-info/METADATA
powerletrics-0.0.5.dist-info/WHEEL
powerletrics-0.0.5.dist-info/entry_points.txt
powerletrics-0.0.5.dist-info/top_level.txt
powerletrics-0.0.5.dist-info/RECORD
