Metadata-Version: 2.1
Name: powerletrics
Version: 0.0.5
Summary: A program that brings power estimation per process to your Linux system
Author-email: Didi Hoffmann <powerletrics@ribalba.de>
License:                     GNU AFFERO GENERAL PUBLIC LICENSE
Project-URL: Homepage, https://github.com/green-kernel/powerletrics
Project-URL: Issues, https://github.com/green-kernel/powerletrics/issues
Classifier: Programming Language :: Python :: 3
Classifier: Development Status :: 2 - Pre-Alpha
Classifier: Environment :: Console
Classifier: License :: OSI Approved :: GNU Affero General Public License v3 or later (AGPLv3+)
Requires-Python: >=3.11
License-File: LICENSE
